hi/__init__.py
python_hi-0.1.3.dist-info/METADATA
python_hi-0.1.3.dist-info/WHEEL
python_hi-0.1.3.dist-info/entry_points.txt
python_hi-0.1.3.dist-info/RECORD
